NiukeWangMingqiXiaozhaoBishiZhentiJingxuanJishuPian20202021/README.md
NiukeWangMingqiXiaozhaoBishiZhentiJingxuanJishuPian20202021/__init__.py
NiukeWangMingqiXiaozhaoBishiZhentiJingxuanJishuPian20202021/__main__.py
NiukeWangMingqiXiaozhaoBishiZhentiJingxuanJishuPian20202021/file.epub
NiukeWangMingqiXiaozhaoBishiZhentiJingxuanJishuPian20202021/index.html
NiukeWangMingqiXiaozhaoBishiZhentiJingxuanJishuPian20202021/css/__init__.py
NiukeWangMingqiXiaozhaoBishiZhentiJingxuanJishuPian20202021/css/annotations.css
NiukeWangMingqiXiaozhaoBishiZhentiJingxuanJishuPian20202021/css/main.css
NiukeWangMingqiXiaozhaoBishiZhentiJingxuanJishuPian20202021/css/normalize.css
NiukeWangMingqiXiaozhaoBishiZhentiJingxuanJishuPian20202021/css/popup.css
NiukeWangMingqiXiaozhaoBishiZhentiJingxuanJishuPian20202021/font/__init__.py
NiukeWangMingqiXiaozhaoBishiZhentiJingxuanJishuPian20202021/font/fontello.eot
NiukeWangMingqiXiaozhaoBishiZhentiJingxuanJishuPian20202021/font/fontello.svg
NiukeWangMingqiXiaozhaoBishiZhentiJingxuanJishuPian20202021/font/fontello.ttf
NiukeWangMingqiXiaozhaoBishiZhentiJingxuanJishuPian20202021/font/fontello.woff
NiukeWangMingqiXiaozhaoBishiZhentiJingxuanJishuPian20202021/img/__init__.py
NiukeWangMingqiXiaozhaoBishiZhentiJingxuanJishuPian20202021/img/annotator-glyph-sprite.png
NiukeWangMingqiXiaozhaoBishiZhentiJingxuanJishuPian20202021/img/annotator-icon-sprite.png
NiukeWangMingqiXiaozhaoBishiZhentiJingxuanJishuPian20202021/img/apple-touch-icon.png
NiukeWangMingqiXiaozhaoBishiZhentiJingxuanJishuPian20202021/img/cancelfullscreen.png
NiukeWangMingqiXiaozhaoBishiZhentiJingxuanJishuPian20202021/img/close.png
NiukeWangMingqiXiaozhaoBishiZhentiJingxuanJishuPian20202021/img/fullscreen.png
NiukeWangMingqiXiaozhaoBishiZhentiJingxuanJishuPian20202021/img/loader.gif
NiukeWangMingqiXiaozhaoBishiZhentiJingxuanJishuPian20202021/img/menu-icon.png
NiukeWangMingqiXiaozhaoBishiZhentiJingxuanJishuPian20202021/img/save.png
niuke_wang_mingqi_xiaozhao_bishi_zhenti_jingxuan_jishu_pian_2020_2021-2024.3.5.0.dist-info/METADATA
niuke_wang_mingqi_xiaozhao_bishi_zhenti_jingxuan_jishu_pian_2020_2021-2024.3.5.0.dist-info/WHEEL
niuke_wang_mingqi_xiaozhao_bishi_zhenti_jingxuan_jishu_pian_2020_2021-2024.3.5.0.dist-info/entry_points.txt
niuke_wang_mingqi_xiaozhao_bishi_zhenti_jingxuan_jishu_pian_2020_2021-2024.3.5.0.dist-info/top_level.txt
niuke_wang_mingqi_xiaozhao_bishi_zhenti_jingxuan_jishu_pian_2020_2021-2024.3.5.0.dist-info/RECORD
